nlptools/__init__.py
nlptools/core/__init__.py
nlptools/core/structures.py
nlptools/core/test_structures.py
nlptools/preloaded/__init__.py
nlptools/preloaded/dictionaries/contractions/english_contractions.json
nlptools/preloaded/dictionaries/lemmas/irregular_noun_dict.p
nlptools/preloaded/dictionaries/lemmas/word_lemma_dict.p
nlptools/preloaded/dictionaries/numerals/enlgish_numerals.json
nlptools/preloaded/lists/__init__.py
nlptools/preloaded/lists/words/__init__.py
nlptools/preloaded/lists/words/english_stopwords.txt
nlptools/preloaded/lists/words/words_alpha.txt
nlptools/preloaded/models/pos_tagging/penn_treebank_crf_postagger.sav
nlptools/preloaded/models/pos_tagging/ud_crf_postagger.sav
nlptools/preloaded/trees/tries/word_trie.p
nlptools/preprocessing/__init__.py
nlptools/preprocessing/featurization.py
nlptools/preprocessing/lemmatization.py
nlptools/preprocessing/normalization.py
nlptools/preprocessing/stemming.py
nlptools/preprocessing/tagging.py
nlptools/preprocessing/test_featurization.py
nlptools/preprocessing/test_lemmatization.py
nlptools/preprocessing/test_normalization.py
nlptools/preprocessing/test_stemming.py
nlptools/preprocessing/test_tagging.py
nlptools/preprocessing/test_tokenization.py
nlptools/preprocessing/tokenization.py
nlptools/test_cases/test_normalize_document_expected.txt
nlptools/test_cases/test_normalize_document_file.txt
nlptools/utils/__init__.py
nlptools/utils/data_structures.py
nlptools/utils/functions.py
nlptools/utils/test_word_utils.py
nlptools/utils/word_utils.py
nlpytools-0.1.0.dist-info/METADATA
nlpytools-0.1.0.dist-info/WHEEL
nlpytools-0.1.0.dist-info/top_level.txt
nlpytools-0.1.0.dist-info/RECORD
