Metadata-Version: 2.1
Name: nlpytools
Version: 0.1.0
Summary: A set of python tools for Natural Language Processing
Home-page: https://github.com/Sirsirious/NLPTools
Author: Tiago Duque
Author-email: tfduque@hotmail.com
License: MIT
Platform: UNKNOWN
Classifier: License :: OSI Approved :: MIT License
Classifier: Programming Language :: Python :: 3
Classifier: Programming Language :: Python :: 3.7
Requires-Dist: numpy
Requires-Dist: sklearn-crfsuite
Requires-Dist: symspellpy
Requires-Dist: tqdm
